s3fs/__init__.py
s3fs/_version.py
s3fs/core.py
s3fs/errors.py
s3fs/mapping.py
s3fs/utils.py
s3fs_itg-0.0.2.dist-info/LICENSE.txt
s3fs_itg-0.0.2.dist-info/METADATA
s3fs_itg-0.0.2.dist-info/WHEEL
s3fs_itg-0.0.2.dist-info/top_level.txt
s3fs_itg-0.0.2.dist-info/RECORD
